peel/__init__.py
peel/peel.py
peel-0.1.0.dist-info/LICENSE
peel-0.1.0.dist-info/METADATA
peel-0.1.0.dist-info/WHEEL
peel-0.1.0.dist-info/top_level.txt
peel-0.1.0.dist-info/RECORD
