Metadata-Version: 2.1
Name: peel
Version: 0.1.0
Summary: Simple web-scraping package
Home-page: https://github.com/mattshaffer11/peel
Author: Matthew Shaffer
Author-email: mattshaffer11@gmail.com
License: MIT license
Keywords: peel
Platform: UNKNOWN
Classifier: Development Status :: 2 - Pre-Alpha
Classifier: Intended Audience :: Developers
Classifier: License :: OSI Approved :: MIT License
Classifier: Natural Language :: English
Classifier: Programming Language :: Python :: 2
Classifier: Programming Language :: Python :: 2.7
Classifier: Programming Language :: Python :: 3
Classifier: Programming Language :: Python :: 3.4
Classifier: Programming Language :: Python :: 3.5
Classifier: Programming Language :: Python :: 3.6
Classifier: Programming Language :: Python :: 3.7
